{
    "id": "CHMZAP",
    "names": [
        {
            "name": "CHMZAP",
            "threshold": 0.85
        },
        {
            "name": "ЧМЗАП",
            "threshold": 0.85
        }
    ],
    "models": {
        "304": {
            "id": "304",
            "names": [
                {
                    "name": "304",
                    "threshold": 1
                }
            ]
        },
        "401": {
            "id": "401",
            "names": [
                {
                    "name": "401",
                    "threshold": 1
                }
            ]
        },
        "402": {
            "id": "402",
            "names": [
                {
                    "name": "402",
                    "threshold": 1
                }
            ]
        },
        "5208": {
            "id": "5208",
            "names": [
                {
                    "name": "5208",
                    "threshold": 1
                }
            ]
        },
        "5523": {
            "id": "5523",
            "names": [
                {
                    "name": "5523",
                    "threshold": 1
                }
            ]
        },
        "5524": {
            "id": "5524",
            "names": [
                {
                    "name": "5524",
                    "threshold": 1
                }
            ]
        },
        "8001": {
            "id": "8001",
            "names": [
                {
                    "name": "8001",
                    "threshold": 1
                }
            ]
        },
        "804": {
            "id": "804",
            "names": [
                {
                    "name": "804",
                    "threshold": 1
                }
            ]
        },
        "8124": {
            "id": "8124",
            "names": [
                {
                    "name": "8124",
                    "threshold": 1
                }
            ]
        },
        "81241": {
            "id": "81241",
            "names": [
                {
                    "name": "81241",
                    "threshold": 1
                }
            ]
        },
        "81243": {
            "id": "81243",
            "names": [
                {
                    "name": "81243",
                    "threshold": 1
                }
            ]
        },
        "8328": {
            "id": "8328",
            "names": [
                {
                    "name": "8328",
                    "threshold": 1
                }
            ]
        },
        "8335": {
            "id": "8335",
            "names": [
                {
                    "name": "8335",
                    "threshold": 1
                }
            ]
        },
        "8358": {
            "id": "8358",
            "names": [
                {
                    "name": "8358",
                    "threshold": 1
                }
            ]
        },
        "8398": {
            "id": "8398",
            "names": [
                {
                    "name": "8398",
                    "threshold": 1
                }
            ]
        },
        "83981": {
            "id": "83981",
            "names": [
                {
                    "name": "83981",
                    "threshold": 1
                }
            ]
        },
        "8399": {
            "id": "8399",
            "names": [
                {
                    "name": "8399",
                    "threshold": 1
                }
            ]
        },
        "83991": {
            "id": "83991",
            "names": [
                {
                    "name": "83991",
                    "threshold": 1
                }
            ]
        },
        "83992": {
            "id": "83992",
            "names": [
                {
                    "name": "83992",
                    "threshold": 1
                }
            ]
        },
        "8554": {
            "id": "8554",
            "names": [
                {
                    "name": "8554",
                    "threshold": 1
                }
            ]
        },
        "85541": {
            "id": "85541",
            "names": [
                {
                    "name": "85541",
                    "threshold": 1
                }
            ]
        },
        "8951": {
            "id": "8951",
            "names": [
                {
                    "name": "8951",
                    "threshold": 1
                }
            ]
        },
        "9012": {
            "id": "9012",
            "names": [
                {
                    "name": "9012",
                    "threshold": 1
                }
            ]
        },
        "93262": {
            "id": "93262",
            "names": [
                {
                    "name": "93262",
                    "threshold": 1
                }
            ]
        },
        "9337": {
            "id": "9337",
            "names": [
                {
                    "name": "9337",
                    "threshold": 1
                }
            ]
        },
        "93371": {
            "id": "93371",
            "names": [
                {
                    "name": "93371",
                    "threshold": 1
                }
            ]
        },
        "938530": {
            "id": "938530",
            "names": [
                {
                    "name": "938530",
                    "threshold": 1
                }
            ]
        },
        "938530040": {
            "id": "938530040",
            "names": [
                {
                    "name": "938530 040",
                    "threshold": 1
                }
            ]
        },
        "9386": {
            "id": "9386",
            "names": [
                {
                    "name": "9386",
                    "threshold": 1
                }
            ]
        },
        "9520": {
            "id": "9520",
            "names": [
                {
                    "name": "9520",
                    "threshold": 1
                }
            ]
        },
        "95201": {
            "id": "95201",
            "names": [
                {
                    "name": "95201",
                    "threshold": 1
                }
            ]
        },
        "9906": {
            "id": "9906",
            "names": [
                {
                    "name": "9906",
                    "threshold": 1
                }
            ]
        },
        "99063": {
            "id": "99063",
            "names": [
                {
                    "name": "99063",
                    "threshold": 1
                }
            ]
        },
        "99064": {
            "id": "99064",
            "names": [
                {
                    "name": "99064",
                    "threshold": 1
                }
            ]
        },
        "99065": {
            "id": "99065",
            "names": [
                {
                    "name": "99065",
                    "threshold": 1
                }
            ]
        },
        "9907": {
            "id": "9907",
            "names": [
                {
                    "name": "9907",
                    "threshold": 1
                }
            ]
        },
        "99072": {
            "id": "99072",
            "names": [
                {
                    "name": "99072",
                    "threshold": 1
                }
            ]
        },
        "9910": {
            "id": "9910",
            "names": [
                {
                    "name": "9910",
                    "threshold": 1
                }
            ]
        },
        "9911": {
            "id": "9911",
            "names": [
                {
                    "name": "9911",
                    "threshold": 1
                }
            ]
        },
        "9985": {
            "id": "9985",
            "names": [
                {
                    "name": "9985",
                    "threshold": 1
                }
            ]
        },
        "99858": {
            "id": "99858",
            "names": [
                {
                    "name": "99858",
                    "threshold": 1
                }
            ]
        },
        "99865": {
            "id": "99865",
            "names": [
                {
                    "name": "99865",
                    "threshold": 1
                }
            ]
        },
        "99874": {
            "id": "99874",
            "names": [
                {
                    "name": "99874",
                    "threshold": 1
                }
            ]
        },
        "9990": {
            "id": "9990",
            "names": [
                {
                    "name": "9990",
                    "threshold": 1
                }
            ]
        },
        "99902": {
            "id": "99902",
            "names": [
                {
                    "name": "99902",
                    "threshold": 1
                }
            ]
        },
        "99903": {
            "id": "99903",
            "names": [
                {
                    "name": "99903",
                    "threshold": 1
                }
            ]
        },
        "999039": {
            "id": "999039",
            "names": [
                {
                    "name": "999039",
                    "threshold": 1
                }
            ]
        },
        "99904": {
            "id": "99904",
            "names": [
                {
                    "name": "99904",
                    "threshold": 1
                }
            ]
        },
        "99905": {
            "id": "99905",
            "names": [
                {
                    "name": "99905",
                    "threshold": 1
                }
            ]
        },
        "99908": {
            "id": "99908",
            "names": [
                {
                    "name": "99908",
                    "threshold": 1
                }
            ]
        },
        "9991": {
            "id": "9991",
            "names": [
                {
                    "name": "9991",
                    "threshold": 1
                }
            ]
        }
    }
}