{
  "id": "GKB",
  "names": [
    {
      "name": "GKB",
      "threshold": 0.97
    },
    {
      "name": "ГКБ",
      "threshold": 0.97
    }
  ],
  "models": {
    "8118": {
      "id": "8118",
      "names": [
        {
          "name": "8118",
          "threshold": 1
        }
      ],
      "sql_id": "3046"
    },
    "817": {
      "id": "817",
      "names": [
        {
          "name": "817",
          "threshold": 1
        }
      ],
      "sql_id": "3047"
    },
    "8183": {
      "id": "8183",
      "names": [
        {
          "name": "8183",
          "threshold": 1
        }
      ],
      "sql_id": "3048"
    },
    "819": {
      "id": "819",
      "names": [
        {
          "name": "819",
          "threshold": 1
        }
      ],
      "sql_id": "3049"
    },
    "8328": {
      "id": "8328",
      "names": [
        {
          "name": "8328",
          "threshold": 1
        }
      ],
      "sql_id": "3050"
    },
    "83412": {
      "id": "83412",
      "names": [
        {
          "name": "83412",
          "threshold": 1
        }
      ],
      "sql_id": "15917"
    },
    "83418": {
      "id": "83418",
      "names": [
        {
          "name": "83418",
          "threshold": 1
        }
      ],
      "sql_id": "15921"
    },
    "8350": {
      "id": "8350",
      "names": [
        {
          "name": "8350",
          "threshold": 1
        }
      ],
      "sql_id": "3051"
    },
    "8352": {
      "id": "8352",
      "names": [
        {
          "name": "8352",
          "threshold": 1
        }
      ],
      "sql_id": "3052"
    },
    "8527": {
      "id": "8527",
      "names": [
        {
          "name": "8527",
          "threshold": 1
        }
      ],
      "sql_id": "3053"
    },
    "8535": {
      "id": "8535",
      "names": [
        {
          "name": "8535",
          "threshold": 1
        }
      ],
      "sql_id": "3054"
    },
    "8551": {
      "id": "8551",
      "names": [
        {
          "name": "8551",
          "threshold": 1
        }
      ],
      "sql_id": "3055"
    }
  }
}