{"id": "KAVZ", "names": [{"name": "KAVZ", "threshold": 0.93}, {"name": "КАВЗ", "threshold": 0.93}], "models": {"324400": {"id": "324400", "names": [{"name": "324400", "threshold": 1}]}, "324410": {"id": "324410", "names": [{"name": "324410", "threshold": 1}]}, "3270": {"id": "3270", "names": [{"name": "3270", "threshold": 1}]}, "3271": {"id": "3271", "names": [{"name": "3271", "threshold": 1}]}, "3976": {"id": "3976", "names": [{"name": "3976", "threshold": 1}]}, "4224": {"id": "4224", "names": [{"name": "4224", "threshold": 1}]}, "4235": {"id": "4235", "names": [{"name": "4235", "threshold": 1}]}, "4238": {"id": "4238", "names": [{"name": "4238", "threshold": 1}]}, "4270": {"id": "4270", "names": [{"name": "4270", "threshold": 1}]}, "685": {"id": "685", "names": [{"name": "685", "threshold": 1}]}, "OTHER": {"id": "OTHER", "names": [{"name": "OTHER", "threshold": 0.85}, {"name": "ОТХЕР", "threshold": 0.85}]}}}